pyve/__init__.py
pyve/cli.py
pyve/manager.py
pyve-1.0.1.dist-info/METADATA
pyve-1.0.1.dist-info/WHEEL
pyve-1.0.1.dist-info/entry_points.txt
pyve-1.0.1.dist-info/top_level.txt
pyve-1.0.1.dist-info/RECORD
