Metadata-Version: 2.4
Name: pyve
Version: 1.0.1
Summary: Comprehensive virtual environment management tool
Author: anhvth5
Project-URL: Homepage, https://github.com/anhvth/speedy_utils
Project-URL: Repository, https://github.com/anhvth/speedy_utils
Keywords: virtual-environment,venv,python,environment-management
Classifier: Development Status :: 5 - Production/Stable
Classifier: Intended Audience :: Developers
Classifier: License :: OSI Approved :: MIT License
Classifier: Operating System :: OS Independent
Classifier: Programming Language :: Python :: 3
Classifier: Programming Language :: Python :: 3.7
Classifier: Programming Language :: Python :: 3.8
Classifier: Programming Language :: Python :: 3.9
Classifier: Programming Language :: Python :: 3.10
Classifier: Programming Language :: Python :: 3.11
Classifier: Programming Language :: Python :: 3.12
Classifier: Topic :: Software Development :: Libraries :: Python Modules
Classifier: Topic :: System :: Systems Administration
Requires-Python: >=3.7
Requires-Dist: json5
Requires-Dist: rich
